drf_tracking_logger/__init__.py
drf_tracking_logger/base_mixins.py
drf_tracking_logger/mixins.py
drf_tracking_logger-1.9.5.dist-info/LICENSE
drf_tracking_logger-1.9.5.dist-info/METADATA
drf_tracking_logger-1.9.5.dist-info/WHEEL
drf_tracking_logger-1.9.5.dist-info/top_level.txt
drf_tracking_logger-1.9.5.dist-info/RECORD
