Metadata-Version: 2.1
Name: drf-tracking-logger
Version: 1.9.5
Summary: Log DRF requests on specified logger
Home-page: https://github.com/singhravi1/drf-tracking-logger
Author: Ravi Singh
Author-email: ravi.singh@startxlabs.com
Classifier: Programming Language :: Python :: 3
Classifier: Operating System :: OS Independent
License-File: LICENSE
